odoo/addons/verbose_name_ticket/__init__.py
odoo/addons/verbose_name_ticket/__manifest__.py
odoo/addons/verbose_name_ticket/models/__init__.py
odoo/addons/verbose_name_ticket/models/helpdesk_ticket.py
odoo12_addon_verbose_name_ticket-12.0.1.0.2.dist-info/METADATA
odoo12_addon_verbose_name_ticket-12.0.1.0.2.dist-info/WHEEL
odoo12_addon_verbose_name_ticket-12.0.1.0.2.dist-info/top_level.txt
odoo12_addon_verbose_name_ticket-12.0.1.0.2.dist-info/RECORD
