Metadata-Version: 2.1
Name: odoo12-addon-verbose-name-ticket
Version: 12.0.1.0.2
Summary: The name printed for each ticket now is built with the number and also the name
Home-page: https://coopdevs.org
Author: Coopdevs Treball SCCL
License: AGPL-3
Platform: UNKNOWN
Classifier: Programming Language :: Python
Classifier: Framework :: Odoo
Classifier: License :: OSI Approved :: GNU Affero General Public License v3
Requires-Python: >=3.5
Requires-Dist: odoo12-addon-helpdesk-mgmt
Requires-Dist: odoo (<12.1dev,>=12.0a)
